trulens/instrument/nemo/__init__.py
trulens/instrument/nemo/py.typed
trulens/instrument/nemo/tru_rails.py
trulens_instrument_nemo-1.0.1a1.dist-info/METADATA
trulens_instrument_nemo-1.0.1a1.dist-info/WHEEL
trulens_instrument_nemo-1.0.1a1.dist-info/RECORD
