Metadata-Version: 2.1
Name: trulens-instrument-nemo
Version: 1.0.1a1
Summary: Library to systematically track and evaluate LLM based applications.
Home-page: https://trulens.org/
License: MIT
Author: Snowflake Inc.
Author-email: ml-observability-wg-dl@snowflake.com
Requires-Python: >=3.9,<3.12
Classifier: Development Status :: 3 - Alpha
Classifier: License :: OSI Approved :: MIT License
Classifier: Operating System :: OS Independent
Classifier: Programming Language :: Python :: 3
Classifier: Programming Language :: Python :: 3.9
Classifier: Programming Language :: Python :: 3.10
Classifier: Programming Language :: Python :: 3.11
Requires-Dist: nemoguardrails (>=0.9,<0.10)
Requires-Dist: pydantic (>=2,<3)
Requires-Dist: trulens-core (>=1.0.0,<2.0.0)
Requires-Dist: trulens-instrument-langchain (>=1.0.0,<2.0.0) ; python_version < "3.13"
Project-URL: Documentation, https://trulens.org/trulens/getting_started/
Project-URL: Repository, https://github.com/truera/trulens
